{
   "abstract" : "a fast CPAN module installer",
   "author" : [
      "Shoichi Kaji <skaji@cpan.org>"
   ],
   "dynamic_config" : 0,
   "generated_by" : "Dist::Milla version v1.0.20, Dist::Zilla version 6.014, CPAN::Meta::Converter version 2.150010",
   "license" : [
      "perl_5"
   ],
   "meta-spec" : {
      "url" : "http://search.cpan.org/perldoc?CPAN::Meta::Spec",
      "version" : 2
   },
   "name" : "App-cpm",
   "no_index" : {
      "directory" : [
         "eg",
         "examples",
         "inc",
         "share",
         "t",
         "xt"
      ]
   },
   "prereqs" : {
      "configure" : {
         "requires" : {
            "Module::Build::Tiny" : "0.034"
         }
      },
      "develop" : {
         "requires" : {
            "Archive::Tar" : "0",
            "Archive::Zip" : "!= 1.66",
            "CPAN::Mirror::Tiny" : "0.20",
            "Capture::Tiny" : "0",
            "Dist::Milla" : "v1.0.20",
            "Path::Tiny" : "0",
            "Test::More" : "0.98",
            "Test::Pod" : "1.41"
         }
      },
      "runtime" : {
         "recommends" : {
            "Carton" : "0",
            "IO::Uncompress::Gunzip" : "0"
         },
         "requires" : {
            "CPAN::Common::Index" : "0",
            "CPAN::DistnameInfo" : "0",
            "CPAN::Meta" : "0",
            "CPAN::Meta::Requirements" : "2.130",
            "CPAN::Meta::YAML" : "0",
            "Class::Tiny" : "0",
            "Command::Runner" : "0.100",
            "ExtUtils::InstallPaths" : "0.002",
            "File::Copy::Recursive" : "0",
            "File::pushd" : "0",
            "HTTP::Tinyish" : "0.12",
            "JSON::PP" : "2.27300",
            "Menlo::CLI::Compat" : "1.9021",
            "Module::CPANfile" : "0",
            "Module::Metadata" : "0",
            "Parallel::Pipes" : "0.004",
            "local::lib" : "2.000018",
            "parent" : "0",
            "perl" : "5.008001",
            "version" : "0.77"
         }
      }
   },
   "provides" : {
      "App::cpm" : {
         "file" : "lib/App/cpm.pm",
         "version" : "0.991"
      },
      "App::cpm::CLI" : {
         "file" : "lib/App/cpm/CLI.pm"
      },
      "App::cpm::CircularDependency" : {
         "file" : "lib/App/cpm/CircularDependency.pm"
      },
      "App::cpm::DistNotation" : {
         "file" : "lib/App/cpm/DistNotation.pm"
      },
      "App::cpm::Distribution" : {
         "file" : "lib/App/cpm/Distribution.pm"
      },
      "App::cpm::HTTP" : {
         "file" : "lib/App/cpm/HTTP.pm"
      },
      "App::cpm::Installer::Unpacker" : {
         "file" : "lib/App/cpm/Installer/Unpacker.pm"
      },
      "App::cpm::Job" : {
         "file" : "lib/App/cpm/Job.pm"
      },
      "App::cpm::Logger" : {
         "file" : "lib/App/cpm/Logger.pm"
      },
      "App::cpm::Logger::File" : {
         "file" : "lib/App/cpm/Logger/File.pm"
      },
      "App::cpm::Master" : {
         "file" : "lib/App/cpm/Master.pm"
      },
      "App::cpm::Requirement" : {
         "file" : "lib/App/cpm/Requirement.pm"
      },
      "App::cpm::Resolver" : {
         "file" : "lib/App/cpm/Resolver.pm"
      },
      "App::cpm::Resolver::02Packages" : {
         "file" : "lib/App/cpm/Resolver/02Packages.pm"
      },
      "App::cpm::Resolver::CPANfile" : {
         "file" : "lib/App/cpm/Resolver/CPANfile.pm"
      },
      "App::cpm::Resolver::Cascade" : {
         "file" : "lib/App/cpm/Resolver/Cascade.pm"
      },
      "App::cpm::Resolver::MetaCPAN" : {
         "file" : "lib/App/cpm/Resolver/MetaCPAN.pm"
      },
      "App::cpm::Resolver::MetaDB" : {
         "file" : "lib/App/cpm/Resolver/MetaDB.pm"
      },
      "App::cpm::Resolver::Snapshot" : {
         "file" : "lib/App/cpm/Resolver/Snapshot.pm"
      },
      "App::cpm::Tutorial" : {
         "file" : "lib/App/cpm/Tutorial.pm"
      },
      "App::cpm::Util" : {
         "file" : "lib/App/cpm/Util.pm"
      },
      "App::cpm::Worker" : {
         "file" : "lib/App/cpm/Worker.pm"
      },
      "App::cpm::Worker::Installer" : {
         "file" : "lib/App/cpm/Worker/Installer.pm"
      },
      "App::cpm::Worker::Installer::Menlo" : {
         "file" : "lib/App/cpm/Worker/Installer/Menlo.pm"
      },
      "App::cpm::Worker::Installer::Prebuilt" : {
         "file" : "lib/App/cpm/Worker/Installer/Prebuilt.pm"
      },
      "App::cpm::Worker::Resolver" : {
         "file" : "lib/App/cpm/Worker/Resolver.pm"
      },
      "App::cpm::version" : {
         "file" : "lib/App/cpm/version.pm"
      }
   },
   "release_status" : "stable",
   "resources" : {
      "bugtracker" : {
         "web" : "https://github.com/skaji/cpm/issues"
      },
      "homepage" : "https://github.com/skaji/cpm",
      "repository" : {
         "type" : "git",
         "url" : "https://github.com/skaji/cpm.git",
         "web" : "https://github.com/skaji/cpm"
      }
   },
   "version" : "0.991",
   "x_contributors" : [
      "Andrew Rodland <andrew@cleverdomain.org>",
      "Dave Rolsky <autarch@urth.org>",
      "Felix Ostmann <felix.ostmann@gmail.com>",
      "Kenichi Ishigaki <ishigaki@cpan.org>",
      "Mikhail Ivanov <m.ivanych@gmail.com>",
      "Nicolas R <atoomic@cpan.org>",
      "Nicolas R <cpan@atoomic.org>",
      "Olaf Alders <olaf@wundersolutions.com>",
      "Shoichi Kaji <skaji@outlook.com>",
      "Will Sheppard <will.sheppard.uk@gmail.com>"
   ],
   "x_generated_by_perl" : "v5.30.2",
   "x_serialization_backend" : "Cpanel::JSON::XS version 4.19",
   "x_spdx_expression" : "Artistic-1.0-Perl OR GPL-1.0-or-later",
   "x_static_install" : 1
}

